miidl/__init__.py
miidl/core.py
miidl/IO/__init__.py
miidl/IO/methods.py
miidl/QC/__init__.py
miidl/QC/methods.py
miidl/imputation/__init__.py
miidl/imputation/methods.py
miidl/interpretation/__init__.py
miidl/interpretation/methods.py
miidl/modeling/__init__.py
miidl/modeling/methods.py
miidl/normalization/__init__.py
miidl/normalization/methods.py
miidl/reshaping/__init__.py
miidl/reshaping/methods.py
miidl/utils/__init__.py
miidl/utils/arg_parser.py
miidl/utils/pipeline.py
miidl-0.0.5.dist-info/LICENSE
miidl-0.0.5.dist-info/METADATA
miidl-0.0.5.dist-info/WHEEL
miidl-0.0.5.dist-info/entry_points.txt
miidl-0.0.5.dist-info/top_level.txt
miidl-0.0.5.dist-info/RECORD
