Metadata-Version: 2.1
Name: miidl
Version: 0.0.5
Summary: A Python package for microbial biomarkers identification powered by interpretable deep learning
Home-page: https://github.com/chunribu/miidl/
Author: chunribu
Author-email: chunribu@mail.sdu.edu.cn
License: MIT
Keywords: biomarker interpretable deeplearning
Platform: UNKNOWN
Classifier: Operating System :: POSIX :: Linux
Classifier: Operating System :: MacOS :: MacOS X
Classifier: Operating System :: Microsoft :: Windows
Classifier: License :: OSI Approved :: MIT License
Classifier: Programming Language :: Python :: 3
License-File: LICENSE
Requires-Dist: torch
Requires-Dist: torchvision
Requires-Dist: pandas
Requires-Dist: captum
Requires-Dist: scikit-learn
